ansible/plugins/lookup/syspass.py
digdeo_syspass_ansible_lookup-0.3.5.dist-info/licenses/LICENSE.txt
digdeo_syspass_ansible_lookup-0.3.5.dist-info/METADATA
digdeo_syspass_ansible_lookup-0.3.5.dist-info/WHEEL
digdeo_syspass_ansible_lookup-0.3.5.dist-info/top_level.txt
digdeo_syspass_ansible_lookup-0.3.5.dist-info/RECORD
