Metadata-Version: 2.4
Name: digdeo-syspass-ansible-lookup
Version: 0.3.5
Summary: DigDeo Syspass Ansible Lookup
Home-page: https://git.digdeo.fr/digdeo-system/digdeo-syspass-ansible-lookup
Author: DigDeo
Author-email: pierre-henry.muller@digdeo.fr
License: GPL-3.0-or-later
Keywords: DigDeo Syspass Ansible Lookup
Classifier: Development Status :: 5 - Production/Stable
Classifier: Intended Audience :: Developers
Classifier: Intended Audience :: System Administrators
Classifier: Topic :: Software Development :: Libraries :: Python Modules
Classifier: Topic :: Security
Classifier: Programming Language :: Python
Classifier: Programming Language :: Python :: 2.7
Classifier: Programming Language :: Python :: 3.5
Classifier: Programming Language :: Python :: 3.7
Classifier: Programming Language :: Python :: 3.8
Classifier: Programming Language :: Python :: 3.9
Classifier: Programming Language :: Python :: 3.10
Classifier: Programming Language :: Python :: 3.11
Classifier: Programming Language :: Python :: 3.12
License-File: LICENSE.txt
Requires-Dist: digdeo-syspass-client
Requires-Dist: six
Requires-Dist: colorama
Dynamic: author
Dynamic: author-email
Dynamic: classifier
Dynamic: description
Dynamic: description-content-type
Dynamic: home-page
Dynamic: keywords
Dynamic: license
Dynamic: license-file
Dynamic: requires-dist
Dynamic: summary
